pychkari/__init__.py
pychkari/container.py
pychkari/dependencymanager.py
pychkari/errors.py
pychkari-1.1.2.dist-info/LICENSE
pychkari-1.1.2.dist-info/METADATA
pychkari-1.1.2.dist-info/WHEEL
pychkari-1.1.2.dist-info/top_level.txt
pychkari-1.1.2.dist-info/RECORD
