Metadata-Version: 2.1
Name: pychkari
Version: 1.1.2
Summary: A Very Simple Python Dependency Injector
Home-page: https://github.com/akshay2000/Pychkari
Author: Akshay Zade
Author-email: akshay2000@hotmail.com
License: UNKNOWN
Platform: UNKNOWN
Classifier: Programming Language :: Python :: 3
Classifier: License :: OSI Approved :: GNU General Public License v3 (GPLv3)
Classifier: Operating System :: OS Independent
